mojadata/__init__.py
mojadata/arrowspacetiler2d.py
mojadata/block.py
mojadata/boundingbox.py
mojadata/cleanup.py
mojadata/compressingtiler2d.py
mojadata/compressingtiler3d.py
mojadata/config.py
mojadata/gdaltiler2d.py
mojadata/passthroughgdaltiler2d.py
mojadata/tile.py
mojadata/tiler.py
mojadata/error/__init__.py
mojadata/error/attributenotfounderror.py
mojadata/layer/__init__.py
mojadata/layer/attribute.py
mojadata/layer/discretestacklayer.py
mojadata/layer/layer.py
mojadata/layer/rasterlayer.py
mojadata/layer/regularstacklayer.py
mojadata/layer/stacklayer.py
mojadata/layer/vectorlayer.py
mojadata/layer/filter/__init__.py
mojadata/layer/filter/slicevaluefilter.py
mojadata/layer/filter/valuefilter.py
mojadata/layer/gcbm/__init__.py
mojadata/layer/gcbm/disturbancelayer.py
mojadata/layer/gcbm/transitionrule.py
mojadata/layer/gcbm/transitionrulemanager.py
mojadata/util/__init__.py
mojadata/util/gdal_calc.py
mojadata/util/gdalhelper.py
mojadata/util/log.py
mojadata/util/ogrmerge.py
mojadata/util/projecthelper.py
mojadata/util/rasterclipper.py
mojadata/util/validationhelper.py
mojadata-4.1.5.dist-info/METADATA
mojadata-4.1.5.dist-info/WHEEL
mojadata-4.1.5.dist-info/top_level.txt
mojadata-4.1.5.dist-info/RECORD
